scrall/__init__.py
scrall/__main__.py
scrall/exceptions.py
scrall/log.conf
scrall/parse/__init__.py
scrall/parse/parser.py
scrall/parse/scrall.peg
scrall/parse/visitor.py
scrall-0.15.0.dist-info/licenses/LICENSE
scrall-0.15.0.dist-info/METADATA
scrall-0.15.0.dist-info/WHEEL
scrall-0.15.0.dist-info/entry_points.txt
scrall-0.15.0.dist-info/top_level.txt
scrall-0.15.0.dist-info/RECORD
