Metadata-Version: 2.4
Name: scrall
Version: 0.15.0
Summary: Starr's Concise Relational Action Language - For Shlaer-Mellor Executable UML
Author-email: Leon Starr <leon_starr@modelint.com>
License: MIT License
Project-URL: repository, https://github.com/modelint/scrall
Project-URL: documentation, https://github.com/modelint/scrall/wiki
Keywords: action language,executable uml,mbse,xuml,xtuml,platform independent,sysml
Classifier: License :: OSI Approved :: MIT License
Classifier: Programming Language :: Python
Classifier: Programming Language :: Python :: 3
Requires-Python: >=3.10
License-File: LICENSE
Requires-Dist: Arpeggio
Requires-Dist: tomli; python_version < "3.11"
Provides-Extra: build
Requires-Dist: build; extra == "build"
Requires-Dist: twine; extra == "build"
Provides-Extra: dev
Requires-Dist: bump2version; extra == "dev"
Requires-Dist: pytest; extra == "dev"
Dynamic: license-file
